{
  "candidate_id": 340151,
  "candidate_name": "धन बहादुर मास्की",
  "candidate_party": "नेपाल कम्युनिष्ट पार्टी (माओवादी केन्द्र)",
  "candidate_party_logo": "https://upload.wikimedia.org/wikipedia/commons/thumb/1/1a/CPN-M_logo.svg/1024px-CPN-M_logo.svg.png",
  "candidates_current_position": "पूर्व आर्थिक मामिला तथा योजना मन्त्री, लुम्बिनी प्रदेश",
  "candidates_current_position_in_party": "प्रदेश कमिटी सदस्य",
  "candidate_picture": "https://result.election.gov.np/Images/Candidate/340151.jpg",
  "election_history": [
    {
      "year": "२०७४",
      "position": "N/A",
      "district": "दाङ",
      "constituency": "N/A",
      "result": "N/A",
      "party": "नेपाल कम्युनिष्ट पार्टी (माओवादी केन्द्र)"
    },
    {
      "year": "२०७९",
      "position": "प्रदेश सभा सदस्य",
      "district": "दाङ",
      "constituency": "क्षेत्र नं. ३ (ख)",
      "result": "विजयी",
      "party": "नेपाल कम्युनिष्ट पार्टी (माओवादी केन्द्र)"
    }
  ],
  "political_history": [
    {
      "event": "प्रदेश सभा सदस्य पदबाट राजीनामा",
      "date": "२०८२-१०-०६",
      "details": "प्रतिनिधि सभा निर्वाचनमा प्रतिस्पर्धा गर्नका लागि लुम्बिनी प्रदेश सभा सदस्य पदबाट औपचारिक रूपमा राजीनामा दिएका हुन्।",
      "link_to_source": "https://nepalnews.com.np/s/politics/3-lumbini-province-assembly-members-resign-for-federal-polls",
      "event_type": "RESIGNATION",
      "event_category": "NEUTRAL"
    },
    {
      "event": "मन्त्री पदबाट पदमुक्त",
      "date": "२०८०-११-२२",
      "details": "केन्द्रमा सत्ता समीकरण परिवर्तन भएसँगै मुख्यमन्त्री डिल्ली बहादुर चौधरीले माओवादी केन्द्रका मन्त्रीहरूलाई बर्खास्त गर्ने क्रममा मास्कीलाई पदमुक्त गरिएको थियो।",
      "link_to_source": "https://risingnepaldaily.com/news/39733",
      "event_type": "OTHER",
      "event_category": "NEUTRAL"
    },
    {
      "event": "लुम्बिनी प्रदेशको बजेट प्रस्तुत",
      "date": "२०८०-०३-०१",
      "details": "आर्थिक मामिला तथा योजना मन्त्रीको रूपमा आर्थिक वर्ष २०८०/८१ को लागि लुम्बिनी प्रदेशको बजेट प्रदेश सभामा प्रस्तुत गरेका थिए।",
      "link_to_source": "https://lumbini.gov.np/wp-content/uploads/2023/06/Budget-Speech-2080-81.pdf",
      "event_type": "MAJOR_ACHIEVEMENT",
      "event_category": "GOOD"
    },
    {
      "event": "आर्थिक मामिला तथा योजना मन्त्रीमा नियुक्त",
      "date": "२०८०-०१-१५",
      "details": "लुम्बिनी प्रदेशको मुख्यमन्त्री डिल्ली बहादुर चौधरीको नेतृत्वमा बनेको सरकारमा आर्थिक मामिला तथा योजना मन्त्रीको महत्त्वपूर्ण जिम्मेवारी पाएका थिए।",
      "link_to_source": "https://risingnepaldaily.com/news/25859",
      "event_type": "MINISTERIAL_APPT",
      "event_category": "GOOD"
    },
    {
      "event": "प्रदेश सभा सदस्यमा निर्वाचित",
      "date": "२०७९-०८-०८",
      "details": "दाङ निर्वाचन क्षेत्र नम्बर ३ (ख) बाट २२,३६२ मत प्राप्त गरी प्रदेश सभा सदस्यमा विजयी भएका थिए। उनले निकटतम प्रतिद्वन्द्वीलाई २,१६९ मतको अन्तरले पराजित गरेका थिए।",
      "link_to_source": "https://ekantipur.com/news/2022/11/24/16692695574363255.html",
      "event_type": "ELECTION_WIN",
      "event_category": "GOOD"
    }
  ],
  "analysis": "धन बहादुर मास्की नेपाल कम्युनिष्ट पार्टी (माओवादी केन्द्र) का दाङ जिल्लाका एक प्रभावशाली नेता हुन्। २०७९ को प्रदेश सभा निर्वाचनमा दाङ ३ (ख) बाट निर्वाचित भएपछि उनले लुम्बिनी प्रदेशको अर्थमन्त्री जस्तो महत्त्वपूर्ण जिम्मेवारी सफलतापूर्वक निर्वाह गरे। उनको कार्यकालमा प्रदेशको बजेट निर्माण र कार्यान्वयनमा सक्रिय भूमिका रहेको देखिन्छ। हालै उनले संघीय राजनीतिमा प्रवेश गर्ने उद्देश्यका साथ प्रदेश सभा सदस्यबाट राजीनामा दिनुले उनको राजनीतिक महत्वाकांक्षा र पार्टीभित्रको बढ्दो प्रभावलाई झल्काउँछ। उनी विरुद्ध हालसम्म कुनै ठूला भ्रष्टाचार वा कानुनी विवादहरू सार्वजनिक भएका छैनन्, जसले उनको राजनीतिक छवि स्वच्छ राखेको छ। दाङमा उनको राम्रो जनमत र सांगठनिक पकड रहेको मानिन्छ।",
  "overall_approval_rating": 82
}