{
  "candidate_id": 340553,
  "candidate_name": "बन्दना श्रेष्ठ",
  "candidate_party": "नेपाल मजदुर किसान पार्टी",
  "candidate_party_logo": "https://upload.wikimedia.org/wikipedia/commons/thumb/1/1e/Nepal_Workers_Peasants_Party_Logo.png/220px-Nepal_Workers_Peasants_Party_Logo.png",
  "candidates_current_position": "राजनीतिकर्मी",
  "candidates_current_position_in_party": "सक्रिय कार्यकर्ता",
  "candidate_picture": "https://result.election.gov.np/Images/Candidate/340553.jpg",
  "election_history": [
    {
      "year": "२०७९",
      "position": "प्रदेश सभा सदस्य",
      "district": "काठमाडौं",
      "constituency": "१० (ख)",
      "result": "पराजित",
      "party": "नेपाल मजदुर किसान पार्टी"
    }
  ],
  "political_history": [
    {
      "event": "२०७९ को प्रदेश सभा निर्वाचनमा सहभागिता",
      "date": "२०७९-०८-०४",
      "details": "काठमाडौं निर्वाचन क्षेत्र नं. १० (ख) बाट बागमती प्रदेश सभा सदस्यका लागि नेपाल मजदुर किसान पार्टीको तर्फबाट उम्मेदवारी दिएकी थिइन्। उनले कुल २९१ मत प्राप्त गर्दै ९औं स्थान हासिल गरेकी थिइन्।",
      "link_to_source": "https://ekantipur.com/election-2079/provincial-assembly/district-27",
      "event_type": "ELECTION_LOSS",
      "event_category": "NEUTRAL"
    },
    {
      "event": "नेपाल मजदुर किसान पार्टीमा आबद्धता",
      "date": "२०७५-०१-०१",
      "details": "बन्दना श्रेष्ठ लामो समयदेखि नेपाल मजदुर किसान पार्टीको वैचारिक सिद्धान्तमा आबद्ध भई काठमाडौं जिल्लामा पार्टीको सांगठनिक विस्तारमा सक्रिय छिन्।",
      "link_to_source": "https://nwpp.org.np/",
      "event_type": "OTHER",
      "event_category": "GOOD"
    },
    {
      "event": "भ्रष्टाचार मुक्त छवि",
      "date": "२०७९-०८-२९",
      "details": "उनको सम्पूर्ण राजनीतिक करियरमा हालसम्म कुनै पनि आर्थिक हिनामिना वा भ्रष्टाचारका काण्डहरूमा संलग्नता भेटिएको छैन। नेमकिपाका अन्य कार्यकर्ता झैं उनी पनि सादा जीवन र स्वच्छ राजनीतिक छविका लागि चिनिन्छिन्।",
      "link_to_source": "https://nepsebajar.com/election/candidates/340553",
      "event_type": "MAJOR_ACHIEVEMENT",
      "event_category": "GOOD"
    }
  ],
  "analysis": "बन्दना श्रेष्ठ नेपाल मजदुर किसान पार्टी (नेमकिपा) की एक निष्ठावान र सक्रिय कार्यकर्ता हुन्। २०७९ सालको आम निर्वाचनमा उनले काठमाडौं निर्वाचन क्षेत्र नं. १० (ख) बाट प्रदेश सभा सदस्यका लागि उम्मेदवारी दिएकी थिइन्। यद्यपि उनले मात्र २९१ मत प्राप्त गरी पराजय भोग्नु पर्यो, तर उनले नेमकिपाको 'मादल' चिह्नलाई काठमाडौंका मतदातामाझ पुर्याउन भूमिका खेलिन्। उनीमाथि कुनै पनि प्रकारका भ्रष्टाचार वा विवादका आरोपहरू छैनन्, जसले उनको राजनीतिक छविलाई सफा राखेको छ। नेमकिपाको क्याडर-आधारित संरचनामा उनी एक अनुशासित सदस्यको रूपमा चिनिन्छिन्। उनको चुनावी नतिजा कमजोर रहे पनि पार्टीको वैचारिक संघर्षमा उनको उपस्थिति निरन्तर रहेको देखिन्छ।",
  "overall_approval_rating": 52
}