{
  "candidate_id": 340754,
  "candidate_name": "जय नारायण काफ्ले",
  "candidate_party": "स्वतन्त्र",
  "candidate_party_logo": "",
  "candidates_current_position": "प्रतिनिधिसभा सदस्य उम्मेदवार (२०७९)",
  "candidates_current_position_in_party": "स्वतन्त्र",
  "candidate_picture": "https://result.election.gov.np/Images/Candidate/340754.jpg",
  "election_history": [
    {
      "year": "२०७९",
      "position": "प्रतिनिधिसभा सदस्य",
      "district": "रुपन्देही",
      "constituency": "३",
      "result": "पराजित",
      "party": "स्वतन्त्र"
    }
  ],
  "political_history": [
    {
      "event": "प्रतिनिधिसभा निर्वाचन २०७९ मा उम्मेदवारी",
      "date": "२०७९-०७-२३",
      "details": "रुपन्देही निर्वाचन क्षेत्र नम्बर ३ बाट प्रतिनिधिसभा सदस्यका लागि स्वतन्त्र उम्मेदवारका रूपमा मनोनयन दर्ता गराई चुनावमा सहभागी।",
      "link_to_source": "https://result.election.gov.np/",
      "event_type": "ELECTION_LOSS",
      "event_category": "NEUTRAL"
    },
    {
      "event": "भ्रष्टाचार मुक्त देश बनाउने अभियान",
      "date": "२०७८-०३-१५",
      "details": "नेपाललाई भ्रष्टाचार मुक्त बनाउने र देशवासीलाई उत्पादनमूलक कार्यमा संलग्न गराउने अजेन्डा सहित सामाजिक अभियानमा सक्रिय।",
      "link_to_source": "https://nepsebajar.com/election/candidate/340754",
      "event_type": "MAJOR_ACHIEVEMENT",
      "event_category": "GOOD"
    },
    {
      "event": "शैक्षिक र सामाजिक अभियान्ताको रूपमा सक्रियता",
      "date": "२०७५-०८-१०",
      "details": "भैरहवा क्षेत्रमा शैक्षिक परामर्श र सामाजिक अभियानका माध्यमबाट युवाहरूलाई सीपमूलक शिक्षा र वैदेशिक रोजगारका विषयमा सचेतना प्रदान।",
      "link_to_source": "https://nepsebajar.com/election/candidate/340754",
      "event_type": "OTHER",
      "event_category": "GOOD"
    }
  ],
  "analysis": "जय नारायण काफ्ले रुपन्देही जिल्लाका एक स्थानीय सामाजिक अभियान्ता र शैक्षिक परामर्शदाता हुन्। उनले २०७९ सालको प्रतिनिधिसभा निर्वाचनमा रुपन्देही क्षेत्र नम्बर ३ बाट स्वतन्त्र उम्मेदवारी दिएका थिए। उनको मुख्य राजनीतिक अजेन्डा भ्रष्टाचार नियन्त्रण, स्थानीय विकास र युवा स्वरोजगार रहेको थियो। स्थापित राजनीतिक दलका हेभीवेट नेताहरू विरुद्ध उम्मेदवारी दिएका कारण उनी स्थानीय स्तरमा चर्चामा रहे तापनि निर्वाचनमा उल्लेख्य मत प्राप्त गर्न सकेनन्। उनी मुख्यतया भैरहवा क्षेत्रको नागरिक समाजमा सक्रिय छन् र विशेषगरी शैक्षिक क्षेत्रमा उनको पहिचान रहेको छ। दलगत राजनीतिभन्दा बाहिर रहेर सामाजिक रूपान्तरणको पक्षमा उभिनु उनको प्रमुख विशेषता हो।",
  "overall_approval_rating": 45
}