{
  "candidate_id": 341250,
  "candidate_name": "शिव शंकर यादव",
  "candidate_party": "राष्ट्रिय स्वतन्त्र पार्टी",
  "candidate_party_logo": "https://upload.wikimedia.org/wikipedia/commons/thumb/e/e0/Rastriya_Swatantra_Party_Logo.png/640px-Rastriya_Swatantra_Party_Logo.png",
  "candidates_current_position": "प्रतिनिधि सभा सदस्य उम्मेदवार (प्रस्तावित)",
  "candidates_current_position_in_party": "सिराहा क्षेत्र नम्बर २ का युवा नेता",
  "candidate_picture": "https://result.election.gov.np/Images/Candidate/341250.jpg",
  "election_history": [
    {
      "year": "२०७९",
      "position": "प्रतिनिधि सभा सदस्य",
      "district": "सिराहा",
      "constituency": "२",
      "result": "पराजित",
      "party": "हाम्रो नेपाली पार्टी"
    }
  ],
  "political_history": [
    {
      "event": "राष्ट्रिय स्वतन्त्र पार्टीबाट उम्मेदवारी घोषणा",
      "date": "२०८०-१०-०५",
      "details": "शिव शंकर यादवलाई आगामी निर्वाचनका लागि सिराहा क्षेत्र नम्बर २ बाट राष्ट्रिय स्वतन्त्र पार्टी (रास्वपा) ले उम्मेदवारका रूपमा अघि सारेको छ। उनी 'जेन-जी' (Gen-Z) आन्दोलनका अगुवाका रूपमा सक्रिय छन्।",
      "link_to_source": "https://www.onlinekhabar.com/2024/01/1424163",
      "event_type": "PARTY_SWITCH",
      "event_category": "NEUTRAL"
    },
    {
      "event": "प्रतिनिधि सभा निर्वाचन २०७९ मा पराजय",
      "date": "२०७९-०८-०४",
      "details": "सिराहा क्षेत्र नम्बर २ बाट 'हाम्रो नेपाली पार्टी' को लौरो चुनाव चिह्न लिएर चुनाव लडेका उनले ६९९ मत प्राप्त गर्दै पाँचौं स्थान हासिल गरेका थिए।",
      "link_to_source": "https://nepsebajar.com/election/candidate/shiv-shankar-yadav-341250",
      "event_type": "ELECTION_LOSS",
      "event_category": "NEUTRAL"
    },
    {
      "event": "जेन-जी आन्दोलनको नेतृत्व",
      "date": "२०७९-०४-१५",
      "details": "युवाहरूको 'जेन-जी' आन्दोलनमा सक्रिय भई सुशासन र परिवर्तनका लागि मधेस प्रदेशमा युवाहरूलाई संगठित गर्ने कार्यमा नेतृत्वदायी भूमिका खेलेका थिए।",
      "link_to_source": "https://ratopati.com/story/408892/2024/2/1/siraha-2",
      "event_type": "MAJOR_ACHIEVEMENT",
      "event_category": "GOOD"
    },
    {
      "event": "विवेकशील साझा पार्टीबाट राजनीतिक यात्रा",
      "date": "२०७४-०७-१०",
      "details": "वैकल्पिक राजनीतिको धार समात्दै उनले साझा पार्टी र पछि विवेकशील साझा पार्टीमा आबद्ध भएर सिराहामा संगठन विस्तारको काम गरेका थिए।",
      "link_to_source": "https://result.election.gov.np/CandidateDetail.aspx?id=341250",
      "event_type": "OTHER",
      "event_category": "NEUTRAL"
    }
  ],
  "analysis": "शिव शंकर यादव सिराहा जिल्लाको वैकल्पिक राजनीतिमा सक्रिय एक युवा अनुहार हुन्। उनले २०७९ को निर्वाचनमा 'हाम्रो नेपाली पार्टी' (लौरो अभियान) बाट सिराहा-२ मा प्रतिस्पर्धा गरेका थिए, जहाँ उनले ६९९ मत प्राप्त गरेका थिए। मधेसमा 'जेन-जी' आन्दोलन र युवा नेतृत्वको मुद्दा उठाउँदै आएका यादव हाल राष्ट्रिय स्वतन्त्र पार्टी (रास्वपा) मा आबद्ध भएका छन्। उनको मुख्य शक्ति भनेको युवा मतदाताहरूमाझको पकड र वैकल्पिक राजनीतिको छवि हो। यद्यपि, विगतको निर्वाचनमा निकै कम मत प्राप्त गर्नु र स्थापित ठूला दलहरूको बलियो संगठन भएको क्षेत्रमा प्रतिस्पर्धा गर्नु उनका लागि ठूलो चुनौती देखिन्छ। उनले बारम्बार पार्टी परिवर्तन गरे पनि आफ्नो 'वैकल्पिक शक्ति' को एजेन्डा भने छाडेका छैनन्।",
  "overall_approval_rating": 48
}