{
  "candidate_id": 341736,
  "candidate_name": "लाल मुकेश ठाकुर",
  "candidate_party": "स्वतन्त्र",
  "candidate_party_logo": "",
  "candidates_current_position": "राजनीतिकर्मी",
  "candidates_current_position_in_party": "स्वतन्त्र",
  "candidate_picture": "https://result.election.gov.np/Images/Candidate/341736.jpg",
  "election_history": [
    {
      "year": "२०७९",
      "position": "प्रतिनिधि सभा सदस्य",
      "district": "बारा",
      "constituency": "बारा निर्वाचन क्षेत्र नम्बर ३",
      "result": "पराजित",
      "party": "स्वतन्त्र"
    }
  ],
  "political_history": [
    {
      "event": "आम निर्वाचन २०७९ मा स्वतन्त्र उम्मेदवारी",
      "date": "२०७९-०८-०४",
      "details": "लाल मुकेश ठाकुरले २०७९ सालको प्रतिनिधि सभा निर्वाचनमा बारा निर्वाचन क्षेत्र नम्बर ३ बाट स्वतन्त्र उम्मेदवारको रूपमा प्रतिस्पर्धा गरेका थिए। उनी प्रमुख राजनीतिक दलका उम्मेदवारहरूका विरुद्ध चुनावी मैदानमा उत्रिएका थिए।",
      "link_to_source": "https://inseconline.org/ne/news/%E0%A4%AE%E0%A4%A7%E0%A5%87%E0%A4%B6-%E0%A4%AA%E0%A5%8D%E0%A4%B0%E0%A4%A7%E0%A5%87%E0%A4%B6%E0%A4%AE%E0%A4%BE-%E0%A4%AA%E0%A5%8D%E0%A4%B0%E0%A4%A4%E0%A4%B2%E0%A4%A8%E0%A4%A7%E0%A4%B2%E0%A4%B8%E0%A4%AD/",
      "event_type": "ELECTION_LOSS",
      "event_category": "NEUTRAL"
    },
    {
      "event": "स्थानीय स्तरमा राजनीतिक सक्रियता",
      "date": "२०७९-०७-२३",
      "details": "निर्वाचनको क्रममा उनले बाराका स्थानीय मुद्दाहरू र विकासका आवश्यकताहरूलाई उठाएर मतदाताहरू माझ पुगेका थिए। उनले दलीय राजनीति भन्दा बाहिर रहेर जनताको सेवा गर्ने प्रतिबद्धता जनाएका थिए।",
      "link_to_source": "https://nepsebajar.com/election/candidates/341736",
      "event_type": "OTHER",
      "event_category": "NEUTRAL"
    }
  ],
  "analysis": "लाल मुकेश ठाकुर बारा जिल्लाका एक स्थानीय राजनीतिक व्यक्तित्व हुन्। उनले २०७९ सालको आम निर्वाचनमा बारा क्षेत्र नम्बर ३ बाट प्रतिनिधि सभा सदस्यका लागि स्वतन्त्र उम्मेदवारी दिएका थिए। मुख्य राजनीतिक शक्तिहरूको प्रभाव रहेको यस क्षेत्रमा स्वतन्त्र उम्मेदवारका रूपमा उनको उपस्थिति रहनुले स्थानीय स्तरमा केही वैकल्पिक सोचको प्रतिनिधित्व गर्दछ। उनको राजनीतिक प्रभाव हाललाई सीमित क्षेत्रमा मात्र देखिएको छ र उनी कुनै ठूला दलसँग आबद्ध छैनन्। उनको विरुद्धमा हालसम्म कुनै ठूला भ्रष्टाचार वा कानुनी विवादहरू सार्वजनिक भएका छैनन्, तर निर्वाचनमा जित हासिल गर्न उनलाई बलियो सांगठनिक आधारको अभाव देखिएको छ।",
  "overall_approval_rating": 42
}