{
  "candidate_id": 342665,
  "candidate_name": "नविन कुमार यादव",
  "candidate_party": "स्वतन्त्र",
  "candidate_party_logo": "",
  "candidates_current_position": "युवा राजनीतिज्ञ",
  "candidates_current_position_in_party": "स्वतन्त्र",
  "candidate_picture": "https://result.election.gov.np/Images/Candidate/342665.jpg",
  "election_history": [
    {
      "year": "२०७९",
      "position": "प्रतिनिधि सभा सदस्य",
      "district": "सिराहा",
      "constituency": "सिराहा ३",
      "result": "पराजित",
      "party": "स्वतन्त्र"
    }
  ],
  "political_history": [
    {
      "event": "प्रतिनिधि सभा निर्वाचन २०७९ मा स्वतन्त्र उम्मेदवारी",
      "date": "२०७९-०७-२३",
      "details": "सिराहा क्षेत्र नं ३ बाट प्रतिनिधि सभा सदस्यका लागि स्वतन्त्र उम्मेदवारी दर्ता। उनले ११,१४१ मत प्राप्त गरी तेस्रो स्थान हासिल गरेका थिए।",
      "link_to_source": "https://election.ekantipur.com/pratinidhi-sabha-2079/siraha-3?lng=nep",
      "event_type": "ELECTION_LOSS",
      "event_category": "NEUTRAL"
    },
    {
      "event": "पार्टी निर्णय विरुद्ध विद्रोह (बागी उम्मेदवारी)",
      "date": "२०७९-०६-२३",
      "details": "तत्कालीन जनता समाजवादी पार्टी (जसपा) मा आबद्ध रहेका यादवले पार्टीले टिकट नदिएपछि विद्रोह गरी स्वतन्त्र उम्मेदवारी दिएका थिए। उनले एमाले-जसपा गठबन्धनका उम्मेदवार लिलानाथ श्रेष्ठ विरुद्ध प्रतिस्पर्धा गरेका थिए।",
      "link_to_source": "https://shilapatra.com/detail/95171",
      "event_type": "PARTY_SWITCH",
      "event_category": "BAD"
    },
    {
      "event": "पारिवारिक राजनीतिक विरासत",
      "date": "२०७०-०१-०१",
      "details": "नविन कुमार यादव पूर्व मन्त्री राजेन्द्र यादवका छोरा हुन्। उनलाई आफ्नो बुबाको राजनीतिक प्रभाव र क्षेत्रमा रहेको पारिवारिक पकडको लाभ मिलेको देखिन्छ।",
      "link_to_source": "https://nepallive.com/story/297295",
      "event_type": "OTHER",
      "event_category": "NEUTRAL"
    }
  ],
  "analysis": "नविन कुमार यादव सिराहाको राजनीतिमा उदीयमान युवा नेता हुन्। उनी पूर्व मन्त्री राजेन्द्र यादवका छोरा भएकाले उनलाई विरासतको राजनीतिको ठूलो समर्थन छ। २०७९ को निर्वाचनमा जनता समाजवादी पार्टीले टिकट नदिएपछि उनले 'विद्रोही' वा स्वतन्त्र उम्मेदवारका रूपमा निर्वाचन लडेका थिए। उनले ११,१४१ मत प्राप्त गर्नुले क्षेत्रमा उनको व्यक्तिगत र पारिवारिक प्रभाव बलियो रहेको संकेत गर्छ। यद्यपि, उनी निर्वाचनमा तेस्रो स्थानमा खुम्चिएका थिए। सिराहा क्षेत्र नं ३ मा उनको उपस्थितिले मुख्य राजनीतिक दलहरूका लागि चुनौती खडा गरेको देखिन्छ। आगामी दिनमा उनी कुनै स्थापित दलमा फर्कने वा स्वतन्त्र रूपमै संगठन विस्तार गर्ने भन्ने विषयले उनको राजनीतिक भविष्य निर्धारण गर्नेछ।",
  "overall_approval_rating": 45
}